{
    "roi_polygon": [
        [
            447,
            309
        ],
        [
            727,
            304
        ],
        [
            1642,
            688
        ],
        [
            661,
            1000
        ]
    ],
    "edge_index": 0,
    "measurements": {
        "(606, 305)": {
            "(632, 330)": 4.0,
            "(684, 355)": 7.0,
            "(752, 391)": 11.0,
            "(859, 448)": 15.0,
            "(1027, 547)": 19.0,
            "(1362, 747)": 23.0
        }
    }
}